dims/__about__.py
dims/__init__.py
dims/__main__.py
dims/utils.py
dims/cli/__init__.py
dims-0.1.0.dist-info/METADATA
dims-0.1.0.dist-info/WHEEL
dims-0.1.0.dist-info/entry_points.txt
dims-0.1.0.dist-info/licenses/LICENSE.txt
dims-0.1.0.dist-info/RECORD
